{
	"name": "Spr_Galho",
	"plugin-id": "Sprite",
	"sid": 355295875536946,
	"isGlobal": false,
	"instanceVariables": [],
	"behaviorTypes": [
		{
			"behaviorId": "Bullet",
			"name": "Projétil",
			"sid": 223523502871916
		}
	],
	"effectTypes": [],
	"animations": {
		"items": [
			{
				"frames": [
					{
						"width": 330,
						"height": 257,
						"originX": 0.5,
						"originY": 0.5,
						"originalSource": "",
						"exportFormat": "lossless",
						"exportQuality": 0.8,
						"imageSpriteId": 1764865,
						"collisionPoly": {
							"points": [
								0,
								1,
								0,
								0,
								1,
								0,
								1,
								1
							]
						},
						"useCollisionPoly": true,
						"duration": 1,
						"tag": ""
					}
				],
				"sid": 418351796600184,
				"name": "Animation 1",
				"isLooping": false,
				"isPingPong": false,
				"repeatCount": 1,
				"repeatTo": 0,
				"speed": 5
			}
		],
		"subfolders": []
	}
}